pie_core/__init__.py
pie_core/annotation_pipeline.py
pie_core/auto.py
pie_core/document.py
pie_core/hf_hub_mixin.py
pie_core/hparams_mixin.py
pie_core/metric.py
pie_core/model.py
pie_core/module_mixins.py
pie_core/preparable.py
pie_core/registrable.py
pie_core/statistic.py
pie_core/taskencoding.py
pie_core/taskmodule.py
pie_core/utils/__init__.py
pie_core/utils/dictionary.py
pie_core/utils/hparams.py
pie_core/utils/hydra.py
pie_core-0.3.1.dist-info/LICENSE
pie_core-0.3.1.dist-info/LICENSES/PYTORCH-LIGHTNING
pie_core-0.3.1.dist-info/LICENSES/THIRD_PARTY_LICENSES.md
pie_core-0.3.1.dist-info/METADATA
pie_core-0.3.1.dist-info/WHEEL
pie_core-0.3.1.dist-info/RECORD
