Metadata-Version: 2.1
Name: pie-core
Version: 0.3.1
Summary: Core modules of PyTorch-IE
Home-page: https://github.com/arnebinder/pie-core
License: MIT
Author: Arne Binder
Author-email: arne.binder@dfki.de
Requires-Python: >=3.9,<4.0
Classifier: Framework :: Pytest
Classifier: License :: OSI Approved :: MIT License
Classifier: Programming Language :: Python
Classifier: Programming Language :: Python :: 3
Classifier: Programming Language :: Python :: 3.9
Classifier: Programming Language :: Python :: 3.10
Classifier: Programming Language :: Python :: 3.11
Classifier: Programming Language :: Python :: 3.12
Classifier: Programming Language :: Python :: 3 :: Only
Requires-Dist: huggingface_hub (>=0.23.4,<0.36.0)
Project-URL: Bug Tracker, https://github.com/arnebinder/pie-core/issues
Project-URL: Changelog, https://github.com/arnebinder/pie-core/releases
Project-URL: Repository, https://github.com/arnebinder/pie-core
